aimemo/__init__.py
aimemo/config.py
aimemo/core.py
aimemo/providers.py
aimemo/storage.py
aimemo-1.0.1.dist-info/licenses/LICENSE
aimemo-1.0.1.dist-info/METADATA
aimemo-1.0.1.dist-info/WHEEL
aimemo-1.0.1.dist-info/top_level.txt
aimemo-1.0.1.dist-info/RECORD
