Metadata-Version: 2.4
Name: aimemo
Version: 1.0.1
Summary: Memory System for AI Conversations
Author-email: Jason <gianghungtien@gmail.com>
License: MIT
Project-URL: Homepage, https://github.com/gianghungtien/aimemo
Project-URL: Repository, https://github.com/gianghungtien/aimemo
Project-URL: Bug Tracker, https://github.com/gianghungtien/aimemo/issues
Keywords: ai,memory,llm,openai,anthropic,agent,assistant
Classifier: Development Status :: 4 - Beta
Classifier: Intended Audience :: Developers
Classifier: License :: OSI Approved :: MIT License
Classifier: Operating System :: OS Independent
Classifier: Programming Language :: Python :: 3
Classifier: Programming Language :: Python :: 3.8
Classifier: Programming Language :: Python :: 3.9
Classifier: Programming Language :: Python :: 3.10
Classifier: Programming Language :: Python :: 3.11
Classifier: Programming Language :: Python :: 3.12
Classifier: Topic :: Scientific/Engineering :: Artificial Intelligence
Classifier: Topic :: Software Development :: Libraries :: Python Modules
Requires-Python: >=3.8
License-File: LICENSE
Requires-Dist: openai>=1.0.0
Provides-Extra: dev
Requires-Dist: pytest>=7.0; extra == "dev"
Requires-Dist: pytest-cov>=4.0; extra == "dev"
Requires-Dist: black>=23.0; extra == "dev"
Requires-Dist: ruff>=0.1.0; extra == "dev"
Provides-Extra: postgres
Requires-Dist: psycopg2-binary>=2.9.0; extra == "postgres"
Provides-Extra: anthropic
Requires-Dist: anthropic>=0.3.0; extra == "anthropic"
Provides-Extra: all
Requires-Dist: psycopg2-binary>=2.9.0; extra == "all"
Requires-Dist: anthropic>=0.3.0; extra == "all"
Requires-Dist: pytest>=7.0; extra == "all"
Requires-Dist: pytest-cov>=4.0; extra == "all"
Requires-Dist: black>=23.0; extra == "all"
Requires-Dist: ruff>=0.1.0; extra == "all"
Dynamic: license-file
